simpleenvs/__init__.py
simpleenvs/benchmark.py
simpleenvs/constants.py
simpleenvs/exceptions.py
simpleenvs/py.typed
simpleenvs/secure.py
simpleenvs/simple.py
simpleenvs/utils.py
simpleenvs_python-1.1.4.dist-info/licenses/LICENSE
simpleenvs_python-1.1.4.dist-info/METADATA
simpleenvs_python-1.1.4.dist-info/WHEEL
simpleenvs_python-1.1.4.dist-info/top_level.txt
simpleenvs_python-1.1.4.dist-info/RECORD
