Metadata-Version: 2.4
Name: SimpleEnvs-Python
Version: 1.1.4
Summary: Ultra-secure, high-performance .env file loader
Author-email: vmintf <vmintf@gmail.com>
Maintainer-email: vmintf <vmintf@gmail.com>
License: MIT
Project-URL: Homepage, https://github.com/vmintf/SimpleEnvs-Python
Project-URL: Documentation, https://vmintf.github.io/SimpleEnvs-Python
Project-URL: Repository, https://github.com/vmintf/SimpleEnvs-Python.git
Project-URL: Bug Tracker, https://github.com/vmintf/SimpleEnvs-Python/issues
Project-URL: Changelog, https://github.com/vmintf/SimpleEnvs-Python/blob/main/CHANGELOG.md
Project-URL: Funding, https://github.com/sponsors/SimpleEnvs-Python
Keywords: environment,env,dotenv,config,security,performance,async,enterprise
Classifier: Development Status :: 5 - Production/Stable
Classifier: Intended Audience :: Developers
Classifier: License :: OSI Approved :: MIT License
Classifier: Operating System :: OS Independent
Classifier: Programming Language :: Python :: 3
Classifier: Programming Language :: Python :: 3.7
Classifier: Programming Language :: Python :: 3.8
Classifier: Programming Language :: Python :: 3.9
Classifier: Programming Language :: Python :: 3.10
Classifier: Programming Language :: Python :: 3.11
Classifier: Programming Language :: Python :: 3.12
Classifier: Programming Language :: Python :: 3.13
Classifier: Topic :: Software Development :: Libraries :: Python Modules
Classifier: Topic :: System :: Systems Administration
Classifier: Topic :: Security
Classifier: Topic :: Utilities
Classifier: Typing :: Typed
Requires-Python: >=3.7
License-File: LICENSE
Requires-Dist: aiofiles>=0.8.0
Provides-Extra: dev
Requires-Dist: pytest>=7.0.0; extra == "dev"
Requires-Dist: pytest-asyncio>=0.21.0; extra == "dev"
Requires-Dist: pytest-cov>=4.0.0; extra == "dev"
Requires-Dist: black>=23.0.0; extra == "dev"
Requires-Dist: isort>=5.12.0; extra == "dev"
Requires-Dist: mypy>=1.0.0; extra == "dev"
Requires-Dist: flake8>=6.0.0; extra == "dev"
Requires-Dist: pre-commit>=3.0.0; extra == "dev"
Provides-Extra: docs
Requires-Dist: mkdocs>=1.4.0; extra == "docs"
Requires-Dist: mkdocs-material>=9.0.0; extra == "docs"
Requires-Dist: mkdocstrings[python]>=0.20.0; extra == "docs"
Provides-Extra: test
Requires-Dist: pytest>=7.0.0; extra == "test"
Requires-Dist: pytest-asyncio>=0.21.0; extra == "test"
Requires-Dist: pytest-cov>=4.0.0; extra == "test"
Requires-Dist: pytest-benchmark>=4.0.0; extra == "test"
Provides-Extra: benchmark
Requires-Dist: python-dotenv>=1.0.0; extra == "benchmark"
Requires-Dist: pytest-benchmark>=4.0.0; extra == "benchmark"
Requires-Dist: memory-profiler>=0.60.0; extra == "benchmark"
Dynamic: license-file
